esac_juice_pyutils/__init__.py
esac_juice_pyutils/commons/__init__.py
esac_juice_pyutils/commons/coord_utils.py
esac_juice_pyutils/commons/env_variables.py
esac_juice_pyutils/commons/json_handler.py
esac_juice_pyutils/commons/md_handler.py
esac_juice_pyutils/commons/my_config_parser.py
esac_juice_pyutils/commons/my_log.py
esac_juice_pyutils/commons/os_utils.py
esac_juice_pyutils/commons/rst_handler.py
esac_juice_pyutils/commons/tds.py
esac_juice_pyutils/commons/tds_spicey.py
esac_juice_pyutils/commons/workingdays.py
esac_juice_pyutils/db/__init__.py
esac_juice_pyutils/db/mysql_connector.py
esac_juice_pyutils/eps/__init__.py
esac_juice_pyutils/eps/eps_def_file_handler.py
esac_juice_pyutils/eps/eps_events.py
esac_juice_pyutils/eps/eps_evf_handler.py
esac_juice_pyutils/eps/event_handler.py
esac_juice_pyutils/files/__init__.py
esac_juice_pyutils/files/compare_files.py
esac_juice_pyutils/files/dir_file_compare.py
esac_juice_pyutils/files/string_handler.py
esac_juice_pyutils/files/string_list_handler.py
esac_juice_pyutils/files/test_compare_files.py
esac_juice_pyutils/gti/__init__.py
esac_juice_pyutils/gti/gti_handler.py
esac_juice_pyutils/numpy/__init__.py
esac_juice_pyutils/numpy/numpy_utils.py
esac_juice_pyutils/periods/__init__.py
esac_juice_pyutils/periods/event_period_merger.py
esac_juice_pyutils/periods/intervals_handler.py
esac_juice_pyutils/periods/series_handler.py
esac_juice_pyutils/plots/__init__.py
esac_juice_pyutils/plots/matplotlib_utils.py
esac_juice_pyutils/spiceypi/__init__.py
esac_juice_pyutils/spiceypi/gf_distance.py
esac_juice_pyutils/spiceypi/gs_elevation.py
esac_juice_pyutils/spiceypi/gs_occult.py
esac_juice_pyutils/spiceypi/ref_frame.py
esac_juice_pyutils/spiceypi/spice_kernel_utils.py
esac_juice_pyutils/test/__init__.py
esac_juice_pyutils/test/sqlite3_handler.py
esac_juice_pyutils/test/test_env_variables.py
esac_juice_pyutils/test/test_mk_utils.py
esac_juice_pyutils/test/test_my_jason_handler.py
esac_juice_pyutils/test/test_os_utils.py
esac_juice_pyutils-0.3.2.dist-info/METADATA
esac_juice_pyutils-0.3.2.dist-info/WHEEL
esac_juice_pyutils-0.3.2.dist-info/top_level.txt
esac_juice_pyutils-0.3.2.dist-info/RECORD
