Metadata-Version: 2.1
Name: esac_juice_pyutils
Version: 0.3.2
Summary: Python package that provides commons libraries and tools for the JUICE SOC
Home-page: https://juigitlab.esac.esa.int/core-system/uplink/esac_juice_pyutils
Author: JUICE SOC team
Author-email: juice_soc@cosmos.esa.int
Requires-Dist: numpy>=1.21.6
Requires-Dist: six>=1.16
Requires-Dist: pandas>=1.1.5
Requires-Dist: spiceypy>=5.1.2
Requires-Dist: matplotlib>=3.5.3
Requires-Dist: docutils>=0.19
Requires-Dist: pypandoc>=1.11
Requires-Dist: wget>=3.2
